{"nodes": [{"id": "readme_stock", "label": "README-stock.md \u2014 Skladovost p\u0159es Google Sheets n\u00e1vod", "file_type": "document", "source_file": "README-stock.md", "source_location": null, "source_url": null, "captured_at": null, "author": null, "contributor": null}, {"id": "readme_stock_google_sheet_sklad", "label": "Google Sheet \"Sklad\" (stock data source)", "file_type": "concept", "source_file": "README-stock.md", "source_location": null, "source_url": null, "captured_at": null, "author": null, "contributor": null}, {"id": "readme_stock_products_ts", "label": "products.ts (product slug/color/size source of truth)", "file_type": "code", "source_file": "README-stock.md", "source_location": null, "source_url": null, "captured_at": null, "author": null, "contributor": null}, {"id": "readme_stock_google_sheets_api", "label": "Google Sheets API", "file_type": "concept", "source_file": "README-stock.md", "source_location": null, "source_url": null, "captured_at": null, "author": null, "contributor": null}, {"id": "readme_stock_service_account", "label": "Service Account auth (private sheet alternative)", "file_type": "rationale", "source_file": "README-stock.md", "source_location": null, "source_url": null, "captured_at": null, "author": null, "contributor": null}, {"id": "readme_stock_google_auth_library", "label": "google-auth-library (npm package)", "file_type": "code", "source_file": "README-stock.md", "source_location": null, "source_url": null, "captured_at": null, "author": null, "contributor": null}, {"id": "readme_stock_lib_stock_ts", "label": "lib/stock.ts (fetch + cache logic)", "file_type": "code", "source_file": "README-stock.md", "source_location": null, "source_url": null, "captured_at": null, "author": null, "contributor": null}, {"id": "readme_stock_app_produkt_slug_page_tsx", "label": "app/produkt/[slug]/page.tsx (server component)", "file_type": "code", "source_file": "README-stock.md", "source_location": null, "source_url": null, "captured_at": null, "author": null, "contributor": null}, {"id": "readme_stock_app_api_stock_route_ts", "label": "app/api/stock/route.ts (client refresh endpoint)", "file_type": "code", "source_file": "README-stock.md", "source_location": null, "source_url": null, "captured_at": null, "author": null, "contributor": null}, {"id": "readme_stock_components_produktclient_tsx", "label": "components/ProduktClient.tsx (client component)", "file_type": "code", "source_file": "README-stock.md", "source_location": null, "source_url": null, "captured_at": null, "author": null, "contributor": null}, {"id": "readme_stock_getproductstock", "label": "getProductStock()", "file_type": "code", "source_file": "README-stock.md", "source_location": null, "source_url": null, "captured_at": null, "author": null, "contributor": null}, {"id": "readme_stock_lookupstock", "label": "lookupStock()", "file_type": "code", "source_file": "README-stock.md", "source_location": null, "source_url": null, "captured_at": null, "author": null, "contributor": null}, {"id": "readme_stock_stockbadge", "label": "StockBadge (UI component)", "file_type": "code", "source_file": "README-stock.md", "source_location": null, "source_url": null, "captured_at": null, "author": null, "contributor": null}, {"id": "readme_stock_cache_ttl", "label": "CACHE_TTL (3-minute cache mechanism)", "file_type": "rationale", "source_file": "README-stock.md", "source_location": null, "source_url": null, "captured_at": null, "author": null, "contributor": null}, {"id": "readme_stock_env_local", "label": ".env.local environment configuration", "file_type": "concept", "source_file": "README-stock.md", "source_location": null, "source_url": null, "captured_at": null, "author": null, "contributor": null}, {"id": "readme_stock_google_sheet_id", "label": "GOOGLE_SHEET_ID (env var)", "file_type": "concept", "source_file": "README-stock.md", "source_location": null, "source_url": null, "captured_at": null, "author": null, "contributor": null}, {"id": "readme_stock_google_sheets_api_key", "label": "GOOGLE_SHEETS_API_KEY (env var)", "file_type": "concept", "source_file": "README-stock.md", "source_location": null, "source_url": null, "captured_at": null, "author": null, "contributor": null}], "edges": [{"source": "readme_stock", "target": "readme_stock_google_sheet_sklad", "relation": "references", "confidence": "EXTRACTED", "confidence_score": 1.0, "source_file": "README-stock.md", "source_location": null, "weight": 1.0}, {"source": "readme_stock", "target": "readme_stock_google_sheets_api", "relation": "references", "confidence": "EXTRACTED", "confidence_score": 1.0, "source_file": "README-stock.md", "source_location": null, "weight": 1.0}, {"source": "readme_stock", "target": "readme_stock_service_account", "relation": "references", "confidence": "EXTRACTED", "confidence_score": 1.0, "source_file": "README-stock.md", "source_location": null, "weight": 1.0}, {"source": "readme_stock", "target": "readme_stock_google_auth_library", "relation": "references", "confidence": "EXTRACTED", "confidence_score": 1.0, "source_file": "README-stock.md", "source_location": null, "weight": 1.0}, {"source": "readme_stock", "target": "readme_stock_lib_stock_ts", "relation": "references", "confidence": "EXTRACTED", "confidence_score": 1.0, "source_file": "README-stock.md", "source_location": null, "weight": 1.0}, {"source": "readme_stock", "target": "readme_stock_app_produkt_slug_page_tsx", "relation": "references", "confidence": "EXTRACTED", "confidence_score": 1.0, "source_file": "README-stock.md", "source_location": null, "weight": 1.0}, {"source": "readme_stock", "target": "readme_stock_app_api_stock_route_ts", "relation": "references", "confidence": "EXTRACTED", "confidence_score": 1.0, "source_file": "README-stock.md", "source_location": null, "weight": 1.0}, {"source": "readme_stock", "target": "readme_stock_components_produktclient_tsx", "relation": "references", "confidence": "EXTRACTED", "confidence_score": 1.0, "source_file": "README-stock.md", "source_location": null, "weight": 1.0}, {"source": "readme_stock", "target": "readme_stock_env_local", "relation": "references", "confidence": "EXTRACTED", "confidence_score": 1.0, "source_file": "README-stock.md", "source_location": null, "weight": 1.0}, {"source": "readme_stock", "target": "readme_stock_cache_ttl", "relation": "references", "confidence": "EXTRACTED", "confidence_score": 1.0, "source_file": "README-stock.md", "source_location": null, "weight": 1.0}, {"source": "readme_stock", "target": "readme_stock_products_ts", "relation": "references", "confidence": "EXTRACTED", "confidence_score": 1.0, "source_file": "README-stock.md", "source_location": null, "weight": 1.0}, {"source": "readme_stock_google_sheet_sklad", "target": "readme_stock_products_ts", "relation": "references", "confidence": "EXTRACTED", "confidence_score": 1.0, "source_file": "README-stock.md", "source_location": null, "weight": 1.0}, {"source": "readme_stock_app_produkt_slug_page_tsx", "target": "readme_stock_getproductstock", "relation": "calls", "confidence": "EXTRACTED", "confidence_score": 1.0, "source_file": "README-stock.md", "source_location": null, "weight": 1.0}, {"source": "readme_stock_getproductstock", "target": "readme_stock_google_sheets_api", "relation": "calls", "confidence": "EXTRACTED", "confidence_score": 1.0, "source_file": "README-stock.md", "source_location": null, "weight": 1.0}, {"source": "readme_stock_components_produktclient_tsx", "target": "readme_stock_lookupstock", "relation": "calls", "confidence": "EXTRACTED", "confidence_score": 1.0, "source_file": "README-stock.md", "source_location": null, "weight": 1.0}, {"source": "readme_stock_lookupstock", "target": "readme_stock_stockbadge", "relation": "references", "confidence": "EXTRACTED", "confidence_score": 1.0, "source_file": "README-stock.md", "source_location": null, "weight": 1.0}, {"source": "readme_stock_lib_stock_ts", "target": "readme_stock_getproductstock", "relation": "references", "confidence": "EXTRACTED", "confidence_score": 1.0, "source_file": "README-stock.md", "source_location": null, "weight": 1.0}, {"source": "readme_stock_service_account", "target": "readme_stock_google_auth_library", "relation": "references", "confidence": "EXTRACTED", "confidence_score": 1.0, "source_file": "README-stock.md", "source_location": null, "weight": 1.0}, {"source": "readme_stock_google_auth_library", "target": "readme_stock_lib_stock_ts", "relation": "references", "confidence": "EXTRACTED", "confidence_score": 1.0, "source_file": "README-stock.md", "source_location": null, "weight": 1.0}, {"source": "readme_stock_service_account", "target": "readme_stock_google_sheets_api", "relation": "conceptually_related_to", "confidence": "INFERRED", "confidence_score": 0.85, "source_file": "README-stock.md", "source_location": null, "weight": 1.0}, {"source": "readme_stock_env_local", "target": "readme_stock_google_sheet_id", "relation": "references", "confidence": "EXTRACTED", "confidence_score": 1.0, "source_file": "README-stock.md", "source_location": null, "weight": 1.0}, {"source": "readme_stock_env_local", "target": "readme_stock_google_sheets_api_key", "relation": "references", "confidence": "EXTRACTED", "confidence_score": 1.0, "source_file": "README-stock.md", "source_location": null, "weight": 1.0}, {"source": "readme_stock_google_sheets_api_key", "target": "readme_stock_google_sheets_api", "relation": "conceptually_related_to", "confidence": "INFERRED", "confidence_score": 0.85, "source_file": "README-stock.md", "source_location": null, "weight": 1.0}, {"source": "readme_stock_google_sheet_id", "target": "readme_stock_google_sheet_sklad", "relation": "conceptually_related_to", "confidence": "INFERRED", "confidence_score": 0.85, "source_file": "README-stock.md", "source_location": null, "weight": 1.0}, {"source": "readme_stock_cache_ttl", "target": "readme_stock_lib_stock_ts", "relation": "references", "confidence": "EXTRACTED", "confidence_score": 1.0, "source_file": "README-stock.md", "source_location": null, "weight": 1.0}, {"source": "readme_stock_app_api_stock_route_ts", "target": "readme_stock_lib_stock_ts", "relation": "conceptually_related_to", "confidence": "INFERRED", "confidence_score": 0.75, "source_file": "README-stock.md", "source_location": null, "weight": 1.0}, {"source": "readme_stock_google_sheet_sklad", "target": "readme_stock_lib_stock_ts", "relation": "shares_data_with", "confidence": "INFERRED", "confidence_score": 0.85, "source_file": "README-stock.md", "source_location": null, "weight": 1.0}], "hyperedges": [{"id": "stock_lookup_flow", "label": "Product stock lookup pipeline (customer request to StockBadge render)", "nodes": ["readme_stock_app_produkt_slug_page_tsx", "readme_stock_getproductstock", "readme_stock_google_sheets_api", "readme_stock_components_produktclient_tsx", "readme_stock_lookupstock", "readme_stock_stockbadge"], "relation": "form", "confidence": "EXTRACTED", "confidence_score": 1.0, "source_file": "README-stock.md"}, {"id": "google_sheets_auth_methods", "label": "Alternative Google Sheets authentication strategies", "nodes": ["readme_stock_google_sheets_api", "readme_stock_service_account", "readme_stock_google_auth_library"], "relation": "participate_in", "confidence": "INFERRED", "confidence_score": 0.85, "source_file": "README-stock.md"}, {"id": "stock_env_configuration", "label": "Environment variables required for stock integration", "nodes": ["readme_stock_env_local", "readme_stock_google_sheet_id", "readme_stock_google_sheets_api_key"], "relation": "participate_in", "confidence": "EXTRACTED", "confidence_score": 1.0, "source_file": "README-stock.md"}]}